calendar_pytba/__init__.py
calendar_pytba/main.py
calendar_pytba/utils/__init__.py
calendar_pytba/utils/handler.py
calendar_pytba/utils/text.py
calendar_pytba/utils/types.py
calendar_pytba-1.1.0.dist-info/LICENSE
calendar_pytba-1.1.0.dist-info/METADATA
calendar_pytba-1.1.0.dist-info/WHEEL
calendar_pytba-1.1.0.dist-info/RECORD
