Metadata-Version: 2.1
Name: calendar-pytba
Version: 1.1.0
Summary: 
Author: Pavel Anokhin
Author-email: p.a.anokhin@gmail.com
Requires-Python: >=3.8,<4.0
Classifier: Programming Language :: Python :: 3
Classifier: Programming Language :: Python :: 3.8
Classifier: Programming Language :: Python :: 3.9
Classifier: Programming Language :: Python :: 3.10
Classifier: Programming Language :: Python :: 3.11
Requires-Dist: pytelegrambotapi (>=4.12.0,<5.0.0)
Requires-Dist: python-dateutil (>=2.8.2,<3.0.0)
